manly.py
manly-0.4.1.dist-info/entry_points.txt
manly-0.4.1.dist-info/LICENSE
manly-0.4.1.dist-info/WHEEL
manly-0.4.1.dist-info/METADATA
manly-0.4.1.dist-info/RECORD
