Metadata-Version: 2.1
Name: manly
Version: 0.4.1
Summary: manly
Home-page: https://github.com/carlbordum/manly
License: MIT
Author: Carl Bordum Hansen
Author-email: carl@bordum.dk
Classifier: Intended Audience :: Developers
Classifier: License :: OSI Approved :: MIT License
Classifier: Operating System :: POSIX
Classifier: Topic :: Software Development :: Documentation
Requires-Dist: pytest ~= 3.9.2; extra == "test"
Provides-Extra: test
